Metadata-Version: 2.1
Name: opal-azure-cli-cosmosdb
Version: 0.2.15
Summary: Microsoft Azure Command-Line Tools Cosmos DB Command Module
Home-page: https://github.com/Azure/azure-cli
Author: Microsoft Corporation
Author-email: azpycli@microsoft.com
License: MIT
Platform: UNKNOWN
Classifier: Development Status :: 4 - Beta
Classifier: Intended Audience :: Developers
Classifier: Intended Audience :: System Administrators
Classifier: Programming Language :: Python
Classifier: Programming Language :: Python :: 2
Classifier: Programming Language :: Python :: 2.7
Classifier: Programming Language :: Python :: 3
Classifier: Programming Language :: Python :: 3.4
Classifier: Programming Language :: Python :: 3.5
Classifier: License :: OSI Approved :: MIT License
Requires-Dist: azure-mgmt-cosmosdb (==0.6.1)
Requires-Dist: opal-azure-cli-core (>=2.0.68)
Requires-Dist: azure-cosmos (>=3.0.2)
Requires-Dist: azure-cli-command-modules-nspkg (>=2.0.0)
